MANIFEST.in
README.txt
development.ini.tmpl
setup.cfg
setup.py
test.ini
bin/out_of_copyright_composers
bin/pdw-admin
bin/sound_archive_crawl.pl
bin/sound_archive_crawl.py
data/composers.txt
docs/index.txt
pdw/__init__.py
pdw/cli.py
pdw/consolidate.py
pdw/name.py
pdw/pd.py
pdw/search.py
pdw/serialize.py
pdw/stats.py
pdw/websetup.py
pdw.egg-info/PKG-INFO
pdw.egg-info/SOURCES.txt
pdw.egg-info/dependency_links.txt
pdw.egg-info/entry_points.txt
pdw.egg-info/paste_deploy_config.ini_tmpl
pdw.egg-info/paster_plugins.txt
pdw.egg-info/requires.txt
pdw.egg-info/top_level.txt
pdw/config/__init__.py
pdw/config/environment.py
pdw/config/middleware.py
pdw/config/routing.py
pdw/controllers/__init__.py
pdw/controllers/error.py
pdw/controllers/home.py
pdw/controllers/item.py
pdw/controllers/person.py
pdw/controllers/stats.py
pdw/controllers/template.py
pdw/controllers/work.py
pdw/getdata/__init__.py
pdw/getdata/blsa.py
pdw/getdata/cairns.py
pdw/getdata/charm.py
pdw/getdata/marc.py
pdw/getdata/mb.py
pdw/getdata/mb2dm.py
pdw/getdata/ngcoba.py
pdw/getdata/ngcoba2.py
pdw/getdata/ngcoba_composers.py
pdw/getdata/openlibrary.py
pdw/i18n/__init__.py
pdw/lib/__init__.py
pdw/lib/app_globals.py
pdw/lib/base.py
pdw/lib/database.py
pdw/lib/helpers.py
pdw/model/__init__.py
pdw/model/frbr.py
pdw/model/meta.py
pdw/model/sale.py
pdw/model/types.py
pdw/public/css/display.css
pdw/public/css/extra.css
pdw/public/css/forms.css
pdw/public/css/master.css
pdw/public/css/navigation.css
pdw/public/css/print.css
pdw/public/css/structure.css
pdw/public/images/bull.png
pdw/public/images/icon-delete.png
pdw/public/images/icon-edit.png
pdw/public/images/nav-hook.png
pdw/public/images/top-grad.png
pdw/public/scripts/behaviour.js
pdw/public/scripts/master.js
pdw/public/scripts/prototype.js
pdw/templates/__init__.py
pdw/templates/__init__.pyc
pdw/templates/about.html
pdw/templates/common.html
pdw/templates/getinvolved.html
pdw/templates/home.html
pdw/templates/layout.html
pdw/templates/item/__init__.py
pdw/templates/item/__init__.pyc
pdw/templates/item/index.html
pdw/templates/item/layout.html
pdw/templates/item/list.html
pdw/templates/item/read.html
pdw/templates/item/search.html
pdw/templates/person/__init__.py
pdw/templates/person/__init__.pyc
