Metadata-Version: 1.0
Name: pdw
Version: 0.5
Summary: Public Domain Works Database Code and Web Application.
Home-page: http://www.publicdomainworks.net/
Author: Open Knowledge Foundation
Author-email: info@okfn.org
License: GPL
Download-URL: http://knowledgeforge.net/pdw/hg
Platform: UNKNOWN
